{
  "BP01": {
    "ts": "2026-03-22T01:31:10.998945+00:00",
    "alias": "BP01",
    "nodeId": "!2c24f650",
    "shortName": "BP01",
    "longName": "Bigpolo no1",
    "lastHeard": 1774140988,
    "snr": -9.25,
    "hopsAway": 1,
    "deviceMetrics": {
      "batteryLevel": 92,
      "voltage": 4.08,
      "channelUtilization": 19.933334,
      "airUtilTx": 1.2273889,
      "uptimeSeconds": 10870687
    },
    "environmentMetrics": {
      "temperature": 28.18,
      "relativeHumidity": 62.54778,
      "barometricPressure": 1007.3421,
      "gasResistance": 0,
      "iaq": 0,
      "voltage": 0,
      "current": 0,
      "lux": 0,
      "whiteLux": 0,
      "irLux": 0,
      "uvLux": 0
    },
    "airQualityMetrics": {
      "pm10Standard": 0,
      "pm25Standard": 0,
      "pm100Standard": 0,
      "pm10Environmental": 0,
      "pm25Environmental": 0,
      "pm100Environmental": 0,
      "particles03um": 0,
      "particles05um": 0,
      "particles10um": 0,
      "particles25um": 0,
      "particles50um": 0,
      "particles100um": 0,
      "co2": 0,
      "co2Temperature": 0,
      "co2Humidity": 0,
      "pmTemperature": 0,
      "pmHumidity": 0,
      "pmVocIdx": 0,
      "pmNoxIdx": 0
    },
    "metricsSource": {
      "environment": "BME/IAQ",
      "airQuality": "none"
    }
  },
  "BP02": {
    "ts": "2026-03-22T01:31:10.998945+00:00",
    "alias": "BP02",
    "nodeId": "!9ea1bde0",
    "shortName": "BP02",
    "longName": "Bigpolo no2",
    "lastHeard": 1774139651,
    "snr": 10.75,
    "hopsAway": 0,
    "deviceMetrics": {
      "batteryLevel": 101,
      "voltage": 4.304,
      "channelUtilization": 12.361667,
      "airUtilTx": 1.1223888,
      "uptimeSeconds": 813012
    },
    "environmentMetrics": {
      "temperature": 30.36324,
      "relativeHumidity": 52.79151,
      "barometricPressure": 1014.5039,
      "gasResistance": 554.5407,
      "iaq": 128,
      "voltage": 0,
      "current": 0,
      "lux": 0,
      "whiteLux": 0,
      "irLux": 0,
      "uvLux": 0
    },
    "airQualityMetrics": {
      "pm10Standard": 0,
      "pm25Standard": 0,
      "pm100Standard": 0,
      "pm10Environmental": 0,
      "pm25Environmental": 0,
      "pm100Environmental": 0,
      "particles03um": 0,
      "particles05um": 0,
      "particles10um": 0,
      "particles25um": 0,
      "particles50um": 0,
      "particles100um": 0,
      "co2": 0,
      "co2Temperature": 0,
      "co2Humidity": 0,
      "pmTemperature": 0,
      "pmHumidity": 0,
      "pmVocIdx": 0,
      "pmNoxIdx": 0
    },
    "metricsSource": {
      "environment": "BME/IAQ",
      "airQuality": "none"
    }
  },
  "BP03": {
    "ts": "2026-03-22T01:31:10.998945+00:00",
    "alias": "BP03",
    "nodeId": "!9ea2a9fc",
    "shortName": "a9fc",
    "longName": "Meshtastic a9fc",
    "lastHeard": 1773928496,
    "snr": 0,
    "hopsAway": 0,
    "deviceMetrics": {
      "batteryLevel": 101,
      "voltage": 4.373,
      "channelUtilization": 4.56,
      "airUtilTx": 1.3354167,
      "uptimeSeconds": 352410
    },
    "environmentMetrics": {
      "temperature": 27.712631,
      "relativeHumidity": 57.88269,
      "barometricPressure": 0,
      "gasResistance": 0,
      "iaq": 0,
      "voltage": 0,
      "current": 0,
      "lux": 0,
      "whiteLux": 0,
      "irLux": 0,
      "uvLux": 0
    },
    "airQualityMetrics": {
      "pm10Standard": 0,
      "pm25Standard": 0,
      "pm100Standard": 0,
      "pm10Environmental": 0,
      "pm25Environmental": 0,
      "pm100Environmental": 0,
      "particles03um": 0,
      "particles05um": 0,
      "particles10um": 0,
      "particles25um": 0,
      "particles50um": 0,
      "particles100um": 0,
      "co2": 0,
      "co2Temperature": 0,
      "co2Humidity": 0,
      "pmTemperature": 0,
      "pmHumidity": 0,
      "pmVocIdx": 0,
      "pmNoxIdx": 0
    },
    "metricsSource": {
      "environment": "BME/IAQ",
      "airQuality": "none"
    }
  }
}