{
  "ts": "2026-03-22T00:51:28.450754+00:00",
  "remote": "192.168.99.28",
  "path": "/meter/upload",
  "payload": {
    "eng": "20206.31",
    "Uab": "114.75",
    "Pa": "0.09",
    "Uca": "229.4",
    "PFc": "0.901",
    "Qs": "0.17",
    "Ss": "0.33",
    "datetime": "260322085100",
    "Ic": "2.35",
    "Ib": "0",
    "Ia": "1.18",
    "id": "221008180001",
    "Hz": "59.99",
    "PFs": "0.841",
    "Ubc": "114.65",
    "Pb": "0",
    "Pc": "0.18",
    "PFb": "0",
    "Pall": "0.27",
    "Uc": "114.65",
    "Ub": "0",
    "Ua": "114.75",
    "PFa": "0.718"
  },
  "headers": {
    "content_type": "application/json",
    "user_agent": "ESP8266"
  }
}