{
  "ts": "2026-03-22T02:51:30.447067+00:00",
  "remote": "192.168.99.28",
  "path": "/meter/upload",
  "payload": {
    "eng": "20207.08",
    "Uab": "115.34",
    "Pa": "0.11",
    "Uca": "230.55",
    "PFc": "0.912",
    "Qs": "0.2",
    "Ss": "0.4",
    "datetime": "260322105100",
    "Ic": "2.7",
    "Ib": "0",
    "Ia": "1.43",
    "id": "221008180001",
    "Hz": "60",
    "PFs": "0.868",
    "Ubc": "115.21",
    "Pb": "0",
    "Pc": "0.23",
    "PFb": "0",
    "Pall": "0.35",
    "Uc": "115.21",
    "Ub": "0",
    "Ua": "115.34",
    "PFa": "0.772"
  },
  "headers": {
    "content_type": "application/json",
    "user_agent": "ESP8266"
  }
}