{
  "ts": "2026-03-21T04:51:16.331910+00:00",
  "remote": "192.168.99.28",
  "path": "/meter/upload",
  "payload": {
    "eng": "20197.86",
    "Uab": "115.61",
    "Pa": "0.03",
    "Uca": "231.09",
    "PFc": "0.903",
    "Qs": "0.15",
    "Ss": "0.28",
    "datetime": "260321125100",
    "Ic": "2.05",
    "Ib": "0",
    "Ia": "0.68",
    "id": "221008180001",
    "Hz": "60.08",
    "PFs": "0.822",
    "Ubc": "115.48",
    "Pb": "0",
    "Pc": "0.19",
    "PFb": "0",
    "Pall": "0.23",
    "Uc": "115.48",
    "Ub": "0",
    "Ua": "115.61",
    "PFa": "0.44"
  },
  "headers": {
    "content_type": "application/json",
    "user_agent": "ESP8266"
  }
}